LICENSE
README.md
pyproject.toml
setup.py
src/catii/__init__.py
src/catii/ccubes.py
src/catii/ffuncs.py
src/catii/iindexes.py
src/catii/indxio.py
src/catii/set_operations.pyx
src/catii/xcubes.py
src/catii/xfuncs.py
src/catii.egg-info/PKG-INFO
src/catii.egg-info/SOURCES.txt
src/catii.egg-info/dependency_links.txt
src/catii.egg-info/requires.txt
src/catii.egg-info/top_level.txt
tests/test_ccubes.py
tests/test_iindexes.py
tests/test_iindexes_nonint.py
tests/test_indxio.py
tests/test_set_operations.py
tests/test_xcubes.py