Metadata-Version: 2.4
Name: catii
Version: 1.0.0a15
Summary: A library for N-dimensional categorical data.
Home-page: https://github.com/Crunch-io/catii
Author: Robert Brewer, Slobodan Ilić
Author-email: dev@crunch.io
License-File: LICENSE
Requires-Dist: numpy>=1.15.2
Dynamic: author
Dynamic: author-email
Dynamic: description
Dynamic: description-content-type
Dynamic: home-page
Dynamic: license-file
Dynamic: requires-dist
Dynamic: summary
